{
  "source": "https://cdna.artstation.com/p/assets/images/images/020/214/840/large/kyuyong-eom-sc5-final-art-2.jpg?1566872273",
  "md5": "F1B42F46C42DA97BD46F35D7D61D2BF1",
  "tags": [
    "camille",
    "ferros",
    "setsuna",
    "c",
    "chinese",
    "general",
    "three",
    "kingdoms",
    "l.f.",
    "jiang"
  ],
  "small": {
    "scale": 0.5699999999999996,
    "offset_x": -147,
    "offset_y": -446,
    "size": "small",
    "rotation": 0
  },
  "medium": {
    "scale": 0.3299999999999994,
    "offset_x": -50,
    "offset_y": -207,
    "size": "medium",
    "rotation": 0
  },
  "full": {
    "scale": 0.36999999999999944,
    "offset_x": -2,
    "offset_y": -14,
    "size": "full",
    "rotation": 0
  },
  "version": 2,
  "requeried": false,
  "nsfw": false
}