{
  "source": "https://e0.pxfuel.com/wallpapers/267/159/desktop-wallpaper-kaladin-stormblessed-by-kay-huang-reimagined-stormlight-archive.jpg",
  "md5": "5475D9731932C92AE9538F3A4966E5AB",
  "tags": [
    "brawler",
    "male",
    "human",
    "wizard",
    "characters",
    "character",
    "zombie",
    "apocalypse",
    "leather",
    "armor",
    "plate",
    "zombies",
    "human_made_object",
    "fashion_cosmetics_or_accessories",
    "clothing",
    "under_wear",
    "bra",
    "makorr",
    "rogue",
    "ninja",
    "john",
    "dimayuga",
    "https://www.artstation.com/artwork/8lwwxq",
    "sabrina",
    "a.",
    "salazar",
    "wildwest",
    "challenge",
    "vlad",
    "gheneli",
    "design"
  ],
  "small": {
    "scale": 0.6699999999999997,
    "offset_x": -261.6,
    "offset_y": -323.9999999999997,
    "size": "small",
    "rotation": 0
  },
  "medium": {
    "scale": 0.7099999999999997,
    "offset_x": -169.39999999999986,
    "offset_y": -338.40000000000003,
    "size": "medium",
    "rotation": 0
  },
  "full": {
    "scale": 0.95,
    "offset_x": -71.26851851851825,
    "offset_y": -402.4166666666671,
    "size": "full",
    "rotation": 0
  },
  "version": 2,
  "requeried": false,
  "nsfw": false
}