{
  "source": "https://img.wattpad.com/cover/58123537-352-k160232.jpg",
  "md5": "1D0DAA732BB5A9EC1EF48885D8A98870",
  "tags": [
    ""
  ],
  "small": {
    "scale": 0.5299999999999996,
    "offset_x": -2,
    "offset_y": -5,
    "size": "small",
    "rotation": 0
  },
  "medium": {
    "scale": 0.7499999999999998,
    "offset_x": -161,
    "offset_y": 0,
    "size": "medium",
    "rotation": 0
  },
  "full": {
    "scale": 0.8999999999999999,
    "offset_x": -36,
    "offset_y": 0,
    "size": "full",
    "rotation": 0
  },
  "version": 2,
  "requeried": false,
  "nsfw": false
}