{
  "source": "https://pbs.twimg.com/media/Bf4EnI9CYAAQf3O.jpg",
  "md5": "6677802201BEF66F348A09CCB51686E9",
  "tags": [
    "",
    "human",
    "cleric",
    "warrior",
    "dungeons",
    "dragons",
    "character",
    "lord",
    "rings",
    "medieval",
    "knights",
    "knight",
    "armor",
    "orcs",
    "kings",
    "realm",
    "commanders",
    "denman",
    "rooke",
    "dwarf",
    "https://www.artstation.com/artwork/undead-889a4429-134b-4289-8ff3-abb4d3e67eac",
    "criaturas",
    "aeon",
    "henrique",
    "dld",
    "2020",
    "design",
    "concept",
    "characters"
  ],
  "small": {
    "scale": 1.4200000000000004,
    "offset_x": -333,
    "offset_y": -68,
    "size": "small",
    "rotation": 0
  },
  "medium": {
    "scale": 1.5700000000000005,
    "offset_x": -304,
    "offset_y": -78,
    "size": "medium",
    "rotation": 0
  },
  "full": {
    "scale": 1.4900000000000004,
    "offset_x": -92,
    "offset_y": -56,
    "size": "full",
    "rotation": 0
  },
  "version": 2,
  "requeried": true,
  "nsfw": false
}