{
  "source": "https://i.pinimg.com/564x/81/bb/bf/81bbbfbbc6e15535c007dd2f1781fe43.jpg",
  "md5": "580616975D4D32675650CB8D8F78685B",
  "tags": [
    "werewolves",
    "warrior",
    "black",
    "women",
    "merilliza",
    "chan",
    "dungeons",
    "dragons",
    "science",
    "fiction",
    "artwork",
    "robots",
    "sci-fi",
    "human_made_object",
    "fashion_cosmetics_or_accessories",
    "clothing",
    "dress",
    "formal_dress",
    "rita",
    "bikini.",
    "tag.",
    "lnhoz"
  ],
  "small": {
    "scale": 1.3400000000000003,
    "offset_x": -350,
    "offset_y": -51,
    "size": "small",
    "rotation": 0
  },
  "medium": {
    "scale": 0.7999999999999998,
    "offset_x": -73,
    "offset_y": -46,
    "size": "medium",
    "rotation": 0
  },
  "full": {
    "scale": 1.2699999999999998,
    "offset_x": -4,
    "offset_y": -4,
    "size": "full",
    "rotation": 0
  },
  "version": 2,
  "requeried": true,
  "nsfw": false
}