{
  "source": "https://static.wikia.nocookie.net/salzinwun/images/7/7f/Gorrok.jpg/revision/latest?cb=20200307183812",
  "md5": "D4625834690C82B32CB79E5BCFA624CC",
  "tags": [
    "",
    "valhalla",
    "gates",
    "norse",
    "mythology",
    "yeti",
    "messing",
    "with",
    "sasquatch",
    "jakub",
    "rozalski",
    "2020",
    "concept",
    "epic",
    "dieselpunk"
  ],
  "small": {
    "scale": 1.7200000000000006,
    "offset_x": -634,
    "offset_y": -284,
    "size": "small",
    "rotation": 0
  },
  "medium": {
    "scale": 0.95,
    "offset_x": -221,
    "offset_y": -113,
    "size": "medium",
    "rotation": 0
  },
  "full": {
    "scale": 1.04,
    "offset_x": -148,
    "offset_y": -4,
    "size": "full",
    "rotation": 0
  },
  "version": 2,
  "requeried": true,
  "nsfw": false
}