{
  "source": "https://i.imgur.com/Nrv77Tf.jpeg",
  "md5": "0E5A607BE225D0F14832E4FBBCDB8983",
  "tags": [
    ""
  ],
  "small": {
    "scale": 0.8499999999999999,
    "offset_x": -245,
    "offset_y": -59,
    "size": "small",
    "rotation": 0
  },
  "medium": {
    "scale": 0.96,
    "offset_x": -218,
    "offset_y": -23,
    "size": "medium",
    "rotation": 0
  },
  "full": {
    "scale": 1.11,
    "offset_x": -14,
    "offset_y": -2,
    "size": "full",
    "rotation": 0
  },
  "version": 2,
  "requeried": false,
  "nsfw": false
}