{
  "source": "https://cdnb.artstation.com/p/assets/images/images/007/946/343/large/hoang-l-p-solan-sai-final-small.jpg?1509503575",
  "md5": "A2AAE55D994BECFEF07403BA8F083B99",
  "tags": [
    "male",
    "elf",
    "character",
    "tiefling",
    "bard",
    "concept",
    "dark",
    "world",
    "warcraft",
    "rogue",
    "night",
    "blood",
    "buzzard",
    "lionel",
    "cornelius",
    "jr",
    "yennefer",
    "https://www.artstation.com"
  ],
  "small": {
    "scale": 1.1700000000000002,
    "offset_x": -478,
    "offset_y": -124,
    "size": "small"
  },
  "medium": {
    "scale": 0.9199999999999999,
    "offset_x": -238,
    "offset_y": -89,
    "size": "medium"
  },
  "full": {
    "scale": 1.2900000000000003,
    "offset_x": -201,
    "offset_y": -57,
    "size": "full"
  },
  "version": 2,
  "requeried": false,
  "nsfw": false
}