{
  "source": "https://static.wikia.nocookie.net/westmarchescampaign/images/4/4d/Sile_Portrait.jpg/revision/latest?cb=20191021103836",
  "md5": "B99FEBF47EF3FE651576A5D0739185A9",
  "tags": [
    "person",
    "human",
    "bronze",
    "portrait",
    "photography",
    "face",
    "photo",
    "female",
    "kneeling",
    "armor",
    "sport",
    "sports",
    "aasimar",
    "paladin",
    "fighter",
    "ranger",
    "cleric",
    "oracle"
  ],
  "small": {
    "scale": 1.02,
    "offset_x": -219.3333333333318,
    "offset_y": -26,
    "size": "small"
  },
  "medium": {
    "scale": 1.01,
    "offset_x": -121.99999999999989,
    "offset_y": -27.333333333333456,
    "size": "medium"
  },
  "full": {
    "scale": 1.6300000000000006,
    "offset_x": -93.33333333333326,
    "offset_y": 2.2737367544323206e-13,
    "size": "full"
  },
  "version": 2
}