{
  "source": "https://pictures.hentai-foundry.com/t/Tixnen/817099/Tixnen-817099-Yeselyn.jpg",
  "md5": "37D06DBE0E148A6EEA48DD733F295CFF",
  "tags": [
    "",
    "elf",
    "warrior",
    "female",
    "pencil",
    "drawings",
    "names",
    "human_made_object",
    "fashion_cosmetics_or_accessories",
    "clothing",
    "outer_wear",
    "coat",
    "uie",
    "vu",
    "nguyen",
    "hydestudio",
    "willow",
    "returns",
    "sam",
    "rowan"
  ],
  "small": {
    "scale": 1.4399999999999977,
    "offset_x": -745,
    "offset_y": -374,
    "size": "small",
    "rotation": 0
  },
  "medium": {
    "scale": 0.8899999999999999,
    "offset_x": -357,
    "offset_y": -207,
    "size": "medium",
    "rotation": 0
  },
  "full": {
    "scale": 0.6899999999999997,
    "offset_x": -70,
    "offset_y": -8,
    "size": "full",
    "rotation": 0
  },
  "version": 2,
  "requeried": false,
  "nsfw": false
}