{
  "source": "https://i.pinimg.com/originals/b7/37/20/b737209452ba61952cf84fac8fc731d6.png",
  "md5": "B9F847EF04F423996D93031E16637443",
  "tags": [
    "",
    "magic",
    "gathering",
    "concept",
    "epic",
    "monster",
    "planeswalkers",
    "kratos",
    "orc",
    "warrior",
    "god",
    "war",
    "ghost",
    "sparta",
    "dark",
    "elf",
    "druidess",
    "olie",
    "boldador",
    "hk",
    "jakub",
    "wieczniak",
    "z.w.",
    "gu",
    "samurai",
    "girl",
    "illustration"
  ],
  "small": {
    "scale": 0.7199999999999998,
    "offset_x": -237,
    "offset_y": -48,
    "size": "small",
    "rotation": 0
  },
  "medium": {
    "scale": 0.8799999999999999,
    "offset_x": -230,
    "offset_y": -55,
    "size": "medium",
    "rotation": 0
  },
  "full": {
    "scale": 0.8899999999999999,
    "offset_x": -164,
    "offset_y": -16,
    "size": "full",
    "rotation": 0
  },
  "version": 2,
  "requeried": false,
  "nsfw": false
}