{
  "source": "https://cdnb.artstation.com/p/assets/images/images/009/508/193/large/francell-garrote-paladin-dragon-born-inspired-revise-version.jpg?1519382954",
  "md5": "F495E55F8039D829B9ACEEBCA78FDCE7",
  "tags": [
    ""
  ],
  "small": {
    "scale": 0.7899999999999998,
    "offset_x": -296,
    "offset_y": -135,
    "size": "small",
    "rotation": 0
  },
  "medium": {
    "scale": 1.1,
    "offset_x": -386,
    "offset_y": -189,
    "size": "medium",
    "rotation": 0
  },
  "full": {
    "scale": 0.8099999999999998,
    "offset_x": -56,
    "offset_y": -124,
    "size": "full",
    "rotation": 0
  },
  "version": 2,
  "requeried": false,
  "nsfw": false
}