{
  "source": "https://www.artofmtg.com/wp-content/uploads/2015/07/Faerie-Miscreant-Magic-Origins-Art.jpg",
  "md5": "7DEA7E44A5D5E7D4ECA6BAE5B39D317E",
  "tags": [
    "explore",
    "vraska",
    "quirkilicious",
    "nissa",
    "revane",
    "mtg",
    "fan"
  ],
  "small": {
    "scale": 0.98,
    "offset_x": -455,
    "offset_y": -250,
    "size": "small"
  },
  "medium": {
    "scale": 0.95,
    "offset_x": -361,
    "offset_y": -164,
    "size": "medium"
  },
  "full": {
    "scale": 1.5300000000000005,
    "offset_x": -556,
    "offset_y": -156,
    "size": "full"
  },
  "version": 2,
  "requeried": false,
  "nsfw": false
}