{
  "source": "https://images6.alphacoders.com/801/801378.jpg",
  "md5": "1300FD7B025F8DCF45F04DD12CCA6D7E",
  "tags": [
    ""
  ],
  "small": {
    "scale": 0.22999999999999945,
    "offset_x": -442,
    "offset_y": -107,
    "size": "small",
    "rotation": 0
  },
  "medium": {
    "scale": 0.21999999999999945,
    "offset_x": -314,
    "offset_y": -21,
    "size": "medium",
    "rotation": 0
  },
  "full": {
    "scale": 0.34999999999999953,
    "offset_x": -388,
    "offset_y": -6,
    "size": "full",
    "rotation": 0
  },
  "version": 2,
  "requeried": false,
  "nsfw": false
}