{
  "source": "https://cdnb.artstation.com/p/assets/images/images/022/872/021/large/yoon-seseon-.jpg?1577034119",
  "md5": "0A2F0A51B6CDEEE41A8107D3E2856B0E",
  "tags": [
    "seseon",
    "yoon",
    "darth",
    "talon",
    "paladin",
    "dark",
    "assassin",
    "trish",
    "elf",
    "black",
    "dragon",
    "empress",
    "desire",
    "artwork",
    "character",
    "shadow",
    "warrior",
    "ameonna",
    "magdalena",
    "radziej",
    "2019",
    "demon",
    "lord",
    "dead",
    "dmitry",
    "dalnev",
    "2020",
    "creating",
    "characters"
  ],
  "small": {
    "scale": 0.6499999999999997,
    "offset_x": -478.3999999999991,
    "offset_y": -228.8000000000003,
    "size": "small",
    "rotation": 0
  },
  "medium": {
    "scale": 0.2999999999999994,
    "offset_x": -89.59999999999997,
    "offset_y": -88.79999999999984,
    "size": "medium",
    "rotation": 0
  },
  "full": {
    "scale": 0.37999999999999945,
    "offset_x": -25.62962962962888,
    "offset_y": -86.50000000000023,
    "size": "full",
    "rotation": 0
  },
  "version": 2,
  "requeried": false,
  "nsfw": false
}