{
  "source": "https://i.pinimg.com/564x/cc/6c/fc/cc6cfc0cdf6dccfde417fb9785058ced.jpg",
  "md5": "10CD4786C8BCEC139923A2394689911E",
  "tags": [
    "",
    "samurai",
    "armor",
    "concept",
    "sucker",
    "punch",
    "warrior",
    "drawings",
    "dark",
    "elf",
    "female",
    "assassin",
    "demon",
    "hunter",
    "shadows",
    "game",
    "thrones",
    "kryger",
    "india-lee",
    "crews",
    "character",
    "design",
    "roleplay",
    "characters",
    "ascension",
    "othon",
    "nikolaidis",
    "artwork",
    "pinterest",
    "landsknecht",
    "01",
    "igor",
    "zhovtovsky",
    "https://www.artstation.com/artwork/2yqlv"
  ],
  "small": {
    "scale": 1.3800000000000003,
    "offset_x": -167,
    "offset_y": -149,
    "size": "small",
    "rotation": 0
  },
  "medium": {
    "scale": 0.8299999999999998,
    "offset_x": -15,
    "offset_y": -53,
    "size": "medium",
    "rotation": 0
  },
  "full": {
    "scale": 1.3000000000000003,
    "offset_x": -30,
    "offset_y": -64,
    "size": "full",
    "rotation": 0
  },
  "version": 2,
  "requeried": false,
  "nsfw": false
}