{
  "source": "http://img2.safereactor.cc/pics/post/%D0%92%D0%BE%D0%B8%D0%BD%D1%8B-%28Fantasy%29-Fantasy-art-BoissB---BJ-5319367.jpeg",
  "md5": "BAE5862906C5502DE6320B9F2DC23406",
  "tags": [
    "girl",
    "female",
    "tiefling"
  ],
  "small": {
    "scale": 0.7399999999999998,
    "offset_x": -156,
    "offset_y": -17,
    "size": "small"
  },
  "medium": {
    "scale": 0.8199999999999998,
    "offset_x": -128,
    "offset_y": -11,
    "size": "medium"
  },
  "full": {
    "scale": 1.05,
    "offset_x": -27,
    "offset_y": -5,
    "size": "full"
  },
  "version": 2,
  "requeried": false,
  "nsfw": false
}