{
  "source": "https://cdn.discordapp.com/attachments/1003467566775279686/1119023704861589524/malaroch_a_handsome_African_nobleman_fantasy_character_art_39db5c76-9a55-471f-902b-f92d7a6cc98d.png",
  "md5": "8C89A4B30AE44C5805E73AEBE583767D",
  "tags": [
    "Human",
    "Male",
    "Caster"
  ],
  "small": {
    "scale": 0.4599999999999995,
    "offset_x": -148,
    "offset_y": -8,
    "size": "small",
    "rotation": 0
  },
  "medium": {
    "scale": 0.5699999999999996,
    "offset_x": -107,
    "offset_y": 0,
    "size": "medium",
    "rotation": 0
  },
  "full": {
    "scale": 1,
    "offset_x": -142,
    "offset_y": 0,
    "size": "full",
    "rotation": 0
  },
  "version": 2,
  "requeried": false,
  "nsfw": false
}