{
  "source": "https://i.pinimg.com/564x/fd/b7/7b/fdb77b0e99ab495d0f5e1257b649a867.jpg",
  "md5": "5DC2F374A45D11BB1310B4E404A9A737",
  "tags": [
    "person",
    "human",
    "final fantasy",
    "fish",
    "animal",
    ""
  ],
  "small": {
    "scale": 0.5199999999999996,
    "offset_x": -8,
    "offset_y": -26,
    "size": "small"
  },
  "medium": {
    "scale": 0.7999999999999998,
    "offset_x": -16,
    "offset_y": -55,
    "size": "medium"
  },
  "full": {
    "scale": 1.6000000000000005,
    "offset_x": -26,
    "offset_y": -70,
    "size": "full"
  },
  "version": 2
}