{
  "source": "https://i.pinimg.com/originals/24/89/80/248980373cb860bde3a6dd592f9bce84.jpg",
  "md5": "EAA22BB1D63E37FC585C6CA4C65A76E2",
  "tags": [
    ""
  ],
  "small": {
    "scale": 1.3400000000000003,
    "offset_x": -575,
    "offset_y": -740,
    "size": "small",
    "rotation": 0
  },
  "medium": {
    "scale": 0.5699999999999996,
    "offset_x": -117,
    "offset_y": -302,
    "size": "medium",
    "rotation": 0
  },
  "full": {
    "scale": 0.7399999999999998,
    "offset_x": -4,
    "offset_y": -386,
    "size": "full",
    "rotation": 0
  },
  "version": 2,
  "requeried": false,
  "nsfw": false
}