{
  "source": "https://cdn.donmai.us/original/26/6b/__shihouin_yoruichi_bleach_drawn_by_yupachu__266b155b31130196f2de3060617642bb.jpg",
  "md5": "266B155B31130196F2DE3060617642BB",
  "tags": [
    ""
  ],
  "small": {
    "scale": 0.9700000000000002,
    "offset_x": -151,
    "offset_y": -61,
    "size": "small"
  },
  "medium": {
    "scale": 0.6500000000000001,
    "offset_x": -6,
    "offset_y": -3,
    "size": "medium"
  },
  "full": {
    "scale": 1.1400000000000001,
    "offset_x": -4,
    "offset_y": 0,
    "size": "full"
  },
  "version": 2,
  "requeried": false,
  "nsfw": false
}