{
  "source": "https://cdnb.artstation.com/p/assets/images/images/000/465/037/large/dmitry-prozorov-templar-very-mini.jpg",
  "md5": "4B72354078D336DF8565F4834A5993A1",
  "tags": [
    "sfw",
    "paladin",
    "knight",
    "heavy armor",
    "shield",
    "mace"
  ],
  "small": {
    "scale": 0.6864307597702184,
    "offset_x": 309.27396372691265,
    "offset_y": 358.3492007089767,
    "size": "small"
  },
  "medium": {
    "scale": 0.3942683607361881,
    "offset_x": 515.2279179816886,
    "offset_y": 344.0070240342741,
    "size": "medium"
  },
  "full": {
    "scale": 0.9999999999999998,
    "offset_x": -145.21628534321454,
    "offset_y": -14.793446593588232,
    "size": "full"
  }
}