{
  "source": "https://cdnb.artstation.com/p/assets/images/images/023/039/015/large/yusuf-zmirlin-lily.jpg?1577828876",
  "md5": "B0F373CFCB5535EF3807B279D22F15EA",
  "tags": [
    "female",
    "elf",
    "bard",
    "human",
    "concept",
    "human_made_object",
    "fashion_cosmetics_or_accessories",
    "shoes",
    "boots",
    "character",
    "designs",
    "monica",
    "doss",
    "knight",
    "anna",
    "kharitonova",
    "design",
    "juliana",
    "sci-fi",
    "sketch",
    "cool",
    "anime",
    "girl",
    "tina",
    "wang",
    "yuka",
    "steve",
    "james"
  ],
  "small": {
    "scale": 0.5999999999999968,
    "offset_x": -183,
    "offset_y": -9,
    "size": "small",
    "rotation": 0
  },
  "medium": {
    "scale": 0.46999999999999953,
    "offset_x": -47,
    "offset_y": -4,
    "size": "medium",
    "rotation": 0
  },
  "full": {
    "scale": 0.8799999999999988,
    "offset_x": -60,
    "offset_y": 0,
    "size": "full",
    "rotation": 0
  },
  "version": 2,
  "requeried": false,
  "nsfw": false
}