{
  "source": "https://oir.mobi/uploads/posts/2019-12/1575735216_21-44.jpg",
  "md5": "3CD7CCEBCF6C781E03F02F0333C98EBF",
  "tags": [
    "",
    "red",
    "hair",
    "female",
    "warrior",
    "elves",
    "haired",
    "assassin",
    "world",
    "warcraft",
    "rogue",
    "human_made_object",
    "fashion_cosmetics_or_accessories",
    "shoes",
    "boots",
    "accessories",
    "gloves",
    "jewelry",
    "necklace",
    "d&d",
    "elf",
    "wizard",
    "ian",
    "boe",
    "https://www.artstation.com/artwork/qxob",
    "lupa",
    "mateusz",
    "michalski",
    "https://www.artstation.com/artwork/d4ewe",
    "character",
    "iga",
    "kunoichi",
    "thor",
    "odenson",
    "fighter"
  ],
  "small": {
    "scale": 0.6199999999999997,
    "offset_x": -131.80000000000132,
    "offset_y": -69.80000000000018,
    "size": "small",
    "rotation": 0
  },
  "medium": {
    "scale": 0.97,
    "offset_x": -186.00000000000182,
    "offset_y": -107.80000000000001,
    "size": "medium",
    "rotation": 0
  },
  "full": {
    "scale": 0.8699999999999999,
    "offset_x": -0.7962962962965321,
    "offset_y": -89.7037037037037,
    "size": "full",
    "rotation": 0
  },
  "version": 2,
  "requeried": false,
  "nsfw": false
}