{
  "source": "https://external-preview.redd.it/_hSoX_nGaK60tG88YfgFd53AqN7jJYxNWW78Y7BE2Dk.jpg?auto=webp&s=b87b3a8bdf73a136c640436f2d6577b72abfa0b2",
  "md5": "7844FACC063028FA2B6C2674B7355175",
  "tags": [
    ""
  ],
  "small": {
    "scale": 1.3499999999999952,
    "offset_x": -733,
    "offset_y": -23,
    "size": "small",
    "rotation": 0
  },
  "medium": {
    "scale": 0.9199999999999999,
    "offset_x": -321,
    "offset_y": -25,
    "size": "medium",
    "rotation": 0
  },
  "full": {
    "scale": 1.3900000000000003,
    "offset_x": -496,
    "offset_y": -4,
    "size": "full",
    "rotation": 0
  },
  "version": 2,
  "requeried": false,
  "nsfw": false
}