{
  "source": "https://ricedigital.co.uk/wp-content/uploads/2018/04/sakamoto-review-2.jpg",
  "md5": "857781666FCEEBECF8EEF785B94638AB",
  "tags": [
    "beckett",
    "carmen",
    "cornet",
    "gangrel",
    "ccornet",
    "bloody",
    "games",
    "best-of-vampires",
    "vampire",
    "rogue",
    "drawing",
    "thief",
    "character",
    "concept",
    "knight",
    "armor",
    "leather",
    "assassin",
    "mandalorian",
    "heavy",
    "human_made_object",
    "fashion_cosmetics_or_accessories",
    "clothing",
    "outer_wear",
    "coat",
    "zhihui",
    "su",
    "design",
    "characters",
    "holda",
    "outfit",
    "concept_001",
    "ildiko",
    "toth",
    "female",
    "tiefling",
    "anthony",
    "dipaolo",
    "https://www.artstation.com/artwork/g1zkm"
  ],
  "small": {
    "scale": 1.3700000000000003,
    "offset_x": -631,
    "offset_y": -74,
    "size": "small",
    "rotation": 0
  },
  "medium": {
    "scale": 1.1500000000000001,
    "offset_x": -463,
    "offset_y": -48,
    "size": "medium",
    "rotation": 0
  },
  "full": {
    "scale": 1.6700000000000006,
    "offset_x": -670,
    "offset_y": 0,
    "size": "full",
    "rotation": 0
  },
  "version": 2,
  "requeried": false,
  "nsfw": false
}