{
  "source": "https://i.pinimg.com/originals/48/99/2d/48992d2f047c91e79051bfbe939c5385.png",
  "md5": "0BD7740EB63793DF6A60F7FF859E8437",
  "tags": [
    "person",
    "human",
    "painting",
    "art",
    "sport",
    "sports",
    "bow",
    "archery",
    "cleric"
  ],
  "small": {
    "scale": 1.1,
    "offset_x": -217.60000000000045,
    "offset_y": -40.00000000000006,
    "size": "small"
  },
  "medium": {
    "scale": 0.98,
    "offset_x": -122.39999999999992,
    "offset_y": -43.2000000000001,
    "size": "medium"
  },
  "full": {
    "scale": 1.06,
    "offset_x": -40.046296296296305,
    "offset_y": -17.620370370370154,
    "size": "full"
  },
  "version": 2
}