{
  "source": "http://i.4pcdn.org/tg/1460818111419.jpg",
  "md5": "8E27C620AF26B8131552B58C1D49E80D",
  "tags": [
    ""
  ],
  "small": {
    "scale": 0.3299999999999994,
    "offset_x": -32.23880597014926,
    "offset_y": -19.343283582089526,
    "size": "small",
    "rotation": 0
  },
  "medium": {
    "scale": 0.46999999999999953,
    "offset_x": -15.761194029850799,
    "offset_y": -25.074626865671632,
    "size": "medium",
    "rotation": 0
  },
  "full": {
    "scale": 1,
    "offset_x": 0,
    "offset_y": 0,
    "size": "full",
    "rotation": 0
  },
  "version": 2,
  "requeried": false,
  "nsfw": false
}