{
  "source": "https://i.pinimg.com/564x/e1/45/b7/e145b757f31742de59160e013948d078.jpg",
  "md5": "626AD20F10CE9D830073218C8379B526",
  "tags": [
    ""
  ],
  "small": {
    "scale": 0.7199999999999998,
    "offset_x": -98,
    "offset_y": -50,
    "size": "small",
    "rotation": 0
  },
  "medium": {
    "scale": 0.9299999999999999,
    "offset_x": -37,
    "offset_y": -47,
    "size": "medium",
    "rotation": 0
  },
  "full": {
    "scale": 1.2329166666666669,
    "offset_x": -2,
    "offset_y": -14,
    "size": "full",
    "rotation": 0
  },
  "version": 2,
  "requeried": false,
  "nsfw": false
}