{
  "source": "https://safebooru.org//images/3427/34104c498677e9d69de37ba6eeadd781bd378c76.jpg",
  "md5": "C1B5EB5D5D7433DF7CDBEAE5BE683EA2",
  "tags": [
    ""
  ],
  "small": {
    "scale": 0.2999999999999994,
    "offset_x": -314,
    "offset_y": -44,
    "size": "small",
    "rotation": 0
  },
  "medium": {
    "scale": 0.25999999999999934,
    "offset_x": -129,
    "offset_y": -29,
    "size": "medium",
    "rotation": 0
  },
  "full": {
    "scale": 0.4499999999999995,
    "offset_x": -144,
    "offset_y": -68,
    "size": "full",
    "rotation": 0
  },
  "version": 2,
  "requeried": false,
  "nsfw": false
}