{
  "source": "https://i.pinimg.com/564x/b6/4d/61/b64d610da5acff216a4511e2ed2e2aaf.jpg",
  "md5": "17E045D7D3E95685B9984D2D85C53F2C",
  "tags": [
    "human",
    "female",
    "mage",
    "radha",
    "alice",
    "wonderland",
    "alchemist",
    "fariba",
    "khamseh",
    "character",
    "design"
  ],
  "small": {
    "scale": 0.94,
    "offset_x": -178.79999999999973,
    "offset_y": -87.60000000000014,
    "size": "small",
    "rotation": 0
  },
  "medium": {
    "scale": 0.8599999999999999,
    "offset_x": -75.19999999999982,
    "offset_y": -81.60000000000042,
    "size": "medium",
    "rotation": 0
  },
  "full": {
    "scale": 1.2400000000000002,
    "offset_x": -2.324074074074815,
    "offset_y": -105.6018518518527,
    "size": "full",
    "rotation": 0
  },
  "version": 2,
  "requeried": false,
  "nsfw": false
}