{
  "source": "https://i.pinimg.com/474x/07/5c/27/075c27a45339740850920ad04de45377.jpg",
  "md5": "64DD82611068FEDEF20E81D406A221CF",
  "tags": [
    ""
  ],
  "small": {
    "scale": 1,
    "offset_x": -75,
    "offset_y": -4,
    "size": "small",
    "rotation": 0
  },
  "medium": {
    "scale": 1,
    "offset_x": 0,
    "offset_y": 0,
    "size": "medium",
    "rotation": 0
  },
  "full": {
    "scale": 1.5400000000000005,
    "offset_x": -14,
    "offset_y": -18,
    "size": "full",
    "rotation": 0
  },
  "version": 2,
  "requeried": false,
  "nsfw": false
}