{
  "source": "https://static.wikia.nocookie.net/senkizesshousymphogear/images/5/57/Symphogear_XDU_Card_2438_Clean.png/revision/latest/scale-to-width-down/1000?cb=20200908075616",
  "md5": "5A3C69089516F96DE0179B3B01490795",
  "tags": [
    ""
  ],
  "small": {
    "scale": 0.8099999999999998,
    "offset_x": -315,
    "offset_y": -92,
    "size": "small"
  },
  "medium": {
    "scale": 1.02,
    "offset_x": -387,
    "offset_y": -102,
    "size": "medium"
  },
  "full": {
    "scale": 1.03,
    "offset_x": -168,
    "offset_y": -6,
    "size": "full"
  },
  "version": 2
}