{
  "source": "https://cdnb.artstation.com/p/assets/images/images/023/491/685/large/eve-ventrue-dunkelelfe-as.jpg?1579378600",
  "md5": "62DD49CB279C75FCE3E6DE10AABD5D53",
  "tags": [
    "eve",
    "ventrue",
    "eventrue",
    "professional",
    "digital",
    "artist",
    "kylo",
    "ren.",
    "reeds"
  ],
  "small": {
    "scale": 0.8399999999999999,
    "offset_x": -550.5999999999997,
    "offset_y": -6,
    "size": "small",
    "rotation": 0
  },
  "medium": {
    "scale": 0.6099999999999997,
    "offset_x": -306,
    "offset_y": -0.8000000000000114,
    "size": "medium",
    "rotation": 0
  },
  "full": {
    "scale": 1.12,
    "offset_x": -501.70370370370347,
    "offset_y": -20.018518518518476,
    "size": "full",
    "rotation": 0
  },
  "version": 2,
  "requeried": false,
  "nsfw": false
}