{
  "source": "https://cdnb.artstation.com/p/assets/images/images/027/096/303/medium/kyuyong-eom-15fc-w-5-1.jpg?1590585283",
  "md5": "4190F4AE603334550ED173B4EEE1E60D",
  "tags": [
    "invincible",
    "red",
    "sonya",
    "#1",
    "kyu",
    "yong"
  ],
  "small": {
    "scale": 0.8799999999999999,
    "offset_x": -236.66666666666688,
    "offset_y": -357.0000000000003,
    "size": "small"
  },
  "medium": {
    "scale": 0.37999999999999945,
    "offset_x": -11.333333333333428,
    "offset_y": -126.33333333333329,
    "size": "medium"
  },
  "full": {
    "scale": 0.7899999999999998,
    "offset_x": -10.66666666666697,
    "offset_y": -192.66666666666686,
    "size": "full"
  },
  "version": 2,
  "requeried": false,
  "nsfw": false
}