{
  "source": "https://i.pinimg.com/564x/cc/3e/a6/cc3ea6ce5482c7c59a38c6be168f41a1.jpg",
  "md5": "55B8544D5B21BA92322399D3B8993249",
  "tags": [
    "female",
    "half",
    "elf",
    "paladin",
    "dd",
    "ranger",
    "bard",
    "dark",
    "high",
    "orcs",
    "dwarf",
    "maciej",
    "janik",
    "https://www",
    "dragon",
    "hunter",
    "ilsu",
    "jang",
    "hunters",
    "eagle",
    "knight",
    "daniel",
    "kim",
    "wow",
    "iron",
    "world",
    "warcraft",
    "rogue",
    "spider-man",
    "league",
    "legends",
    "vampire",
    "ruslan",
    "svobodin",
    "winter",
    "nord",
    "warrior",
    "samuel",
    "smith",
    "samo94",
    "jjahawa",
    "ue4",
    "project",
    "haitham",
    "zaki"
  ],
  "small": {
    "scale": 2.0599999999999996,
    "offset_x": -370.99999999999477,
    "offset_y": -191.33333333334832,
    "size": "small",
    "rotation": 0
  },
  "medium": {
    "scale": 1.1,
    "offset_x": -68.99999999999994,
    "offset_y": -15.6666666666749,
    "size": "medium",
    "rotation": 0
  },
  "full": {
    "scale": 1.4600000000000004,
    "offset_x": -33.66666666666754,
    "offset_y": -3.333333333334508,
    "size": "full",
    "rotation": 0
  },
  "version": 2,
  "requeried": false,
  "nsfw": false
}