{
  "source": "https://i.pinimg.com/564x/4e/e4/4e/4ee44ee7c7b771d9512f4dac100189a6.jpg",
  "md5": "FFC276AACE909320751C063F555803C6",
  "tags": [
    "sci-fi",
    "character",
    "concept",
    "sketch",
    "cool",
    "lucas",
    "leger"
  ],
  "small": {
    "scale": 1.2400000000000002,
    "offset_x": -254.39999999999998,
    "offset_y": -149.2,
    "size": "small"
  },
  "medium": {
    "scale": 1.05,
    "offset_x": -129,
    "offset_y": -24,
    "size": "medium"
  },
  "full": {
    "scale": 1.6500000000000006,
    "offset_x": -63,
    "offset_y": -21,
    "size": "full"
  },
  "version": 2,
  "requeried": true
}