{
  "source": "https://i.pinimg.com/originals/39/2c/95/392c95ea1f651bc0fb79bcbf402c644d.jpg",
  "md5": "6741EBA0293925C78448B0DA819866EB",
  "tags": [
    ""
  ],
  "small": {
    "scale": 1,
    "offset_x": -179,
    "offset_y": -23,
    "size": "small",
    "rotation": 0
  },
  "medium": {
    "scale": 1,
    "offset_x": 0,
    "offset_y": 0,
    "size": "medium",
    "rotation": 0
  },
  "full": {
    "scale": 1.7200000000000006,
    "offset_x": -18,
    "offset_y": 0,
    "size": "full",
    "rotation": 0
  },
  "version": 2,
  "requeried": false,
  "nsfw": false
}