{
  "source": "https://img.booru.org/grognard//images/31/0c4f02852a43b9af90078c40777807bf73ebe7eb.png",
  "md5": "92A0848F2F45370BD15131BC92FB8352",
  "tags": [
    ""
  ],
  "small": {
    "scale": 0.94,
    "offset_x": -199,
    "offset_y": -112,
    "size": "small",
    "rotation": 0
  },
  "medium": {
    "scale": 0.48999999999999955,
    "offset_x": -25,
    "offset_y": -9,
    "size": "medium",
    "rotation": 0
  },
  "full": {
    "scale": 1.08,
    "offset_x": -76,
    "offset_y": -28,
    "size": "full",
    "rotation": 0
  },
  "version": 2,
  "requeried": false,
  "nsfw": false
}