{
  "source": "https://cdn.shopify.com/s/files/1/0303/9437/t/3/assets/68e7579c-37e6-46c4-9976-5ea00a966711-9796.jpg?809",
  "md5": "CD7AA50455D92BEA80E404FEDF5B61D5",
  "tags": [
    ""
  ],
  "small": {
    "scale": 1.3700000000000003,
    "offset_x": -372,
    "offset_y": -309,
    "size": "small",
    "rotation": 0
  },
  "medium": {
    "scale": 1,
    "offset_x": -176,
    "offset_y": -197,
    "size": "medium",
    "rotation": 0
  },
  "full": {
    "scale": 1.6000000000000005,
    "offset_x": -212,
    "offset_y": -50,
    "size": "full",
    "rotation": 0
  },
  "version": 2,
  "requeried": false,
  "nsfw": false
}