{
  "source": "http://img10.reactor.cc/pics/post/%D0%AD%D1%80%D0%BE%D1%82%D0%B8%D0%BA%D0%B0-Elsy-Gracie-Kay-Kelsey-5197503.jpeg",
  "md5": "91DE81238EBB929AA976FEC76B0F2793",
  "tags": [
    ""
  ],
  "small": {
    "scale": 0.8599999999999999,
    "offset_x": -309,
    "offset_y": -41,
    "size": "small",
    "rotation": 0
  },
  "medium": {
    "scale": 0.6999999999999997,
    "offset_x": -166,
    "offset_y": -19,
    "size": "medium",
    "rotation": 0
  },
  "full": {
    "scale": 0.97,
    "offset_x": -74,
    "offset_y": -34,
    "size": "full",
    "rotation": 0
  },
  "version": 2,
  "requeried": false,
  "nsfw": false
}