{
  "source": "https://i.pinimg.com/originals/2d/f9/09/2df90971be1877213cf1f8981f3436b8.jpg",
  "md5": "9B8518D5139FF73AE5F315910A515314",
  "tags": [
    ""
  ],
  "small": {
    "scale": 0.39999999999999947,
    "offset_x": -49,
    "offset_y": -13,
    "size": "small",
    "rotation": 0
  },
  "medium": {
    "scale": 0.46999999999999953,
    "offset_x": -6,
    "offset_y": -3,
    "size": "medium",
    "rotation": 0
  },
  "full": {
    "scale": 1.01,
    "offset_x": -2,
    "offset_y": -8,
    "size": "full",
    "rotation": 0
  },
  "version": 2,
  "requeried": false,
  "nsfw": false
}