{
  "source": "https://sun9-42.userapi.com/impf/UhTIBUlnpQ5XRlR42e4K0EXfZJPiPfMqHMthdg/O9qwdjG3zQo.jpg?size=402x604&quality=96&sign=b5a2e9c3ee910637a3c5f2a0e41c20a2&type=album",
  "md5": "EF294DFD10D0120BEEA080AE78779B34",
  "tags": [
    ""
  ],
  "small": {
    "scale": 2.7599999999999847,
    "offset_x": -557.5,
    "offset_y": -247.5,
    "size": "small",
    "rotation": 0
  },
  "medium": {
    "scale": 1.7700000000000007,
    "offset_x": -230.5,
    "offset_y": -112.5,
    "size": "medium",
    "rotation": 0
  },
  "full": {
    "scale": 1.9000000000000008,
    "offset_x": -33,
    "offset_y": -98,
    "size": "full",
    "rotation": 0
  },
  "version": 2,
  "requeried": false,
  "nsfw": false
}