{
  "source": "https://media.discordapp.net/attachments/876427412240478229/1025418216828305488/unknown.png?width=317&height=601",
  "md5": "86B04804F68E101737BB9E0DECB7C7DE",
  "tags": [
    ""
  ],
  "small": {
    "scale": 0.95,
    "offset_x": -45,
    "offset_y": -90,
    "size": "small",
    "rotation": 0
  },
  "medium": {
    "scale": 1.08,
    "offset_x": -9,
    "offset_y": -28,
    "size": "medium",
    "rotation": 0
  },
  "full": {
    "scale": 2.4799999999999907,
    "offset_x": -40,
    "offset_y": -62,
    "size": "full",
    "rotation": 0
  },
  "version": 2,
  "requeried": false,
  "nsfw": false
}