{
  "source": "https://i.pinimg.com/736x/72/04/ba/7204bae39bf514dfb62810e430ca5e9e.jpg",
  "md5": "E13DD956B7DB589F92D4D3FBE2DAC4E1",
  "tags": [
    "person",
    "human",
    "horse",
    "animal",
    "mammal",
    "duel",
    "manga",
    "comics",
    "book",
    ""
  ],
  "small": {
    "scale": 1.9300000000000008,
    "offset_x": -538,
    "offset_y": -94,
    "size": "small"
  },
  "medium": {
    "scale": 1.11,
    "offset_x": -218,
    "offset_y": -47,
    "size": "medium"
  },
  "full": {
    "scale": 1.4600000000000004,
    "offset_x": -180,
    "offset_y": -34,
    "size": "full"
  },
  "version": 2
}