{
  "source": "https://lh5.googleusercontent.com/nKKb7S-tYXz75xiCyId-A4BDxMJ-5_-8z2DZZ3UCgPyKBSAF3TDiptSWpuG8ITQQAZevo_Sdtg0cuM-qxrcreiXsMsaNemNH-7UhzH79QK8OjHaxQStyWPmAoHX50QGpDCyECIto",
  "md5": "40533DCBF132125ACABA961E07CCF0B0",
  "tags": [
    ""
  ],
  "small": {
    "scale": 1.3300000000000003,
    "offset_x": -202,
    "offset_y": -88,
    "size": "small",
    "rotation": 0
  },
  "medium": {
    "scale": 0.8499999999999999,
    "offset_x": -18,
    "offset_y": -35,
    "size": "medium",
    "rotation": 0
  },
  "full": {
    "scale": 1.5600000000000005,
    "offset_x": -26,
    "offset_y": -66,
    "size": "full",
    "rotation": 0
  },
  "version": 2,
  "requeried": false,
  "nsfw": false
}