{
  "source": "https://i.pinimg.com/originals/e5/da/97/e5da978ebcb7b1bfeb21f88fcacf933d.jpg",
  "md5": "63980A15B81539C22FCBCB43C43913D5",
  "tags": [
    ""
  ],
  "small": {
    "scale": 0.7599999999999998,
    "offset_x": -167,
    "offset_y": -14,
    "size": "small",
    "rotation": 0
  },
  "medium": {
    "scale": 0.7499999999999998,
    "offset_x": -49,
    "offset_y": -19,
    "size": "medium",
    "rotation": 0
  },
  "full": {
    "scale": 1.1800000000000002,
    "offset_x": -6,
    "offset_y": 0,
    "size": "full",
    "rotation": 0
  },
  "version": 2,
  "requeried": false,
  "nsfw": false
}