{
  "source": "https://i.pinimg.com/474x/50/e7/55/50e755ed87a3f0eb052a2f729378edea.jpg",
  "md5": "B8B2F6AC7A778D00900D37718C50FBBA",
  "tags": [
    "rpg",
    "character",
    "design",
    "unique",
    "witch",
    "anime",
    "characters",
    "girl",
    "medieval",
    "knights",
    "dark",
    "elf",
    "female",
    "assassin",
    "vampire",
    "knight",
    "manga",
    "paladin",
    "old",
    "stuff.",
    "duong",
    "ct",
    "concept",
    "sketch",
    "song",
    "yueran",
    "warrior"
  ],
  "small": {
    "scale": 0.7899999999999998,
    "offset_x": -77,
    "offset_y": -18,
    "size": "small",
    "rotation": 0
  },
  "medium": {
    "scale": 1.07,
    "offset_x": -99,
    "offset_y": -57,
    "size": "medium",
    "rotation": 0
  },
  "full": {
    "scale": 1.5800000000000005,
    "offset_x": -32,
    "offset_y": -36,
    "size": "full",
    "rotation": 0
  },
  "version": 2,
  "requeried": false,
  "nsfw": false
}