{
  "source": "https://cdn.discordapp.com/attachments/438764637417242634/1069343071873028096/IMG_4960.png",
  "md5": "DF43B6694FF01A9CA587445E510C3388",
  "tags": [
    ""
  ],
  "small": {
    "scale": 0.6599999999999997,
    "offset_x": -140,
    "offset_y": -104,
    "size": "small",
    "rotation": 0
  },
  "medium": {
    "scale": 0.5099999999999996,
    "offset_x": -6,
    "offset_y": -53,
    "size": "medium",
    "rotation": 0
  },
  "full": {
    "scale": 1.03,
    "offset_x": -10,
    "offset_y": 0,
    "size": "full",
    "rotation": 0
  },
  "version": 2,
  "requeried": false,
  "nsfw": false
}