{
  "source": "https://cdn.discordapp.com/attachments/1047697127972798524/1064670349612036206/Fulllength-removebg-preview-removebg-preview-removebg-preview.jpg",
  "md5": "B0DBF2E82E19E2EBD489471E428F829B",
  "tags": [
    "Sarenrae",
    ""
  ],
  "small": {
    "scale": 2.4299999999999935,
    "offset_x": -404.8,
    "offset_y": -190.40000000000006,
    "size": "small",
    "rotation": 0
  },
  "medium": {
    "scale": 1.05,
    "offset_x": -64.80000000000001,
    "offset_y": -64.00000000000006,
    "size": "medium",
    "rotation": 0
  },
  "full": {
    "scale": 1.6900000000000006,
    "offset_x": -1.601851851851734,
    "offset_y": -3.2037037037036953,
    "size": "full",
    "rotation": 0
  },
  "version": 2,
  "requeried": false,
  "nsfw": false
}