{
  "source": "https://cdn.inprnt.com/thumbs/2b/c6/2bc66e5566d1a9cec38ed09b2972829a.jpg?response-cache-control=max-age=2628000",
  "md5": "499A6EE7B5741C0A415AA734141D30BD",
  "tags": [
    "male",
    "elf",
    "druid",
    "female",
    "ranger",
    "characters",
    "dark",
    "knight",
    "returns",
    "arch",
    "kelvin",
    "kurniadi",
    "geralt",
    "color",
    "study",
    "andrea",
    "mazziotti",
    "rogue",
    "nymph",
    "love",
    "elves",
    "high",
    "human_made_object",
    "fashion_cosmetics_or_accessories",
    "clothing",
    "under_wear",
    "panties",
    "nissa",
    "revane",
    "_",
    "tutu",
    "lumber",
    "jack",
    "peacecuit",
    "studio",
    "https://www.artstation.com/artwork/exvw0",
    "siegfried",
    "josé-patricio",
    "aguirre"
  ],
  "small": {
    "scale": 0.6999999999999997,
    "offset_x": -231,
    "offset_y": -35,
    "size": "small",
    "rotation": 0
  },
  "medium": {
    "scale": 0.7199999999999998,
    "offset_x": -122,
    "offset_y": -26,
    "size": "medium",
    "rotation": 0
  },
  "full": {
    "scale": 1.5300000000000005,
    "offset_x": -258,
    "offset_y": -4,
    "size": "full",
    "rotation": 0
  },
  "version": 2,
  "requeried": false,
  "nsfw": false
}