{
  "source": "https://scontent-waw1-1.xx.fbcdn.net/v/t1.15752-9/312902061_472383774704469_7102717080533524788_n.jpg?_nc_cat=105&ccb=1-7&_nc_sid=ae9488&_nc_ohc=QfAnVTiR6nUAX-owbtv&_nc_ht=scontent-waw1-1.xx&oh=03_AdS91Sgu_wtzxMHpboeCbiVEdas8VYgLcJaIypjsxwM14Q&oe=63809040",
  "md5": "9472F7A5AA4EE5EA994377852DCFD5CE",
  "tags": [
    ""
  ],
  "small": {
    "scale": 0.6399999999999997,
    "offset_x": -182.39999999999986,
    "offset_y": -36.000000000000085,
    "size": "small",
    "rotation": 0
  },
  "medium": {
    "scale": 1,
    "offset_x": -262.4,
    "offset_y": -69.60000000000002,
    "size": "medium",
    "rotation": 0
  },
  "full": {
    "scale": 2.04,
    "offset_x": -494.9722222222226,
    "offset_y": -22.425925925925867,
    "size": "full",
    "rotation": 0
  },
  "version": 2,
  "requeried": false,
  "nsfw": false
}