{
  "source": "https://i.pinimg.com/564x/a7/46/28/a7462835a8ce30f9cc1b50d729c28179.jpg",
  "md5": "CAF6347108DDB26FB1B2F413DDF75E68",
  "tags": [
    "person",
    "human",
    "painting",
    "art",
    "sport",
    "sports",
    "archery",
    "bow",
    "archer",
    "vegetation",
    "plant",
    ""
  ],
  "small": {
    "scale": 1.3500000000000005,
    "offset_x": -253.99999999999892,
    "offset_y": -163.99999999999983,
    "size": "small"
  },
  "medium": {
    "scale": 0.7999999999999998,
    "offset_x": -52.666666666666856,
    "offset_y": -45.33333333333357,
    "size": "medium"
  },
  "full": {
    "scale": 1.459999999999998,
    "offset_x": -44.00000000000023,
    "offset_y": -14.6666666666668,
    "size": "full"
  },
  "version": 2
}