{
  "source": "https://i.pinimg.com/564x/57/4c/5b/574c5bc10b239b659caf949a9f27e38b.jpg",
  "md5": "1E767C7450BB9D65C009A08A4F4C4487",
  "tags": [
    ""
  ],
  "small": {
    "scale": 1,
    "offset_x": 0,
    "offset_y": 0,
    "size": "small",
    "rotation": 0
  },
  "medium": {
    "scale": 1,
    "offset_x": 0,
    "offset_y": 0,
    "size": "medium",
    "rotation": 0
  },
  "full": {
    "scale": 1,
    "offset_x": 0,
    "offset_y": 0,
    "size": "full",
    "rotation": 0
  },
  "version": 2,
  "requeried": false,
  "nsfw": false
}