{
  "source": "https://64.media.tumblr.com/692dc7523be4efc25df6442ed406d05d/7f2a4ac6ee5b0b2e-6f/s1280x1920/23231ff07eac08fc418e6737e0c0861b9e5b3b1e.jpg",
  "md5": "79915F0D05B36C5065CA45ACAB94E035",
  "tags": [
    ""
  ],
  "small": {
    "scale": 1.0500000000000005,
    "offset_x": -282,
    "offset_y": -144,
    "size": "small",
    "rotation": 0
  },
  "medium": {
    "scale": 0.9099999999999999,
    "offset_x": -178,
    "offset_y": -126,
    "size": "medium",
    "rotation": 0
  },
  "full": {
    "scale": 1.08,
    "offset_x": -92,
    "offset_y": -22,
    "size": "full",
    "rotation": 0
  },
  "version": 2,
  "requeried": false,
  "nsfw": false
}