{
  "source": "https://cdnb.artstation.com/p/assets/images/images/034/127/943/large/junq-jeon-20-1230.jpg?1611489440",
  "md5": "18CEDDFE9E604684157AD53F61B1BA53",
  "tags": [
    "",
    "female",
    "assassin",
    "cosplay",
    "costumes",
    "20181223",
    "qi",
    "wu"
  ],
  "small": {
    "scale": 0.38999999999999946,
    "offset_x": -207,
    "offset_y": -107,
    "size": "small"
  },
  "medium": {
    "scale": 0.26999999999999946,
    "offset_x": -75,
    "offset_y": -65,
    "size": "medium"
  },
  "full": {
    "scale": 0.4499999999999995,
    "offset_x": -68,
    "offset_y": -58,
    "size": "full"
  },
  "version": 2,
  "requeried": false,
  "nsfw": false
}