{
  "source": "https://rare-gallery.com/thumbnail/417477-artwork-fantasy-art-angel-wings-women.png",
  "md5": "FFD40DBE19C07F25C4DA183D766DADE0",
  "tags": [
    "anime",
    "assassin",
    "mask",
    "masked",
    "character",
    "dark",
    "elf",
    "female",
    "knight",
    "samurai",
    "armor",
    "oz",
    "great",
    "powerful",
    "human_made_object",
    "fashion_cosmetics_or_accessories",
    "shoes",
    "boots",
    "tutorial",
    "https://www.instagram.com",
    "hot",
    "toys",
    "star",
    "wars",
    "clone",
    "girl",
    "wonder",
    "woman",
    "yrno",
    "y",
    "zbrush",
    "bpr",
    "render",
    "test",
    "mak",
    "sallan",
    "\"what",
    "is",
    "broken",
    "can",
    "be",
    "reforged!\"",
    "subin",
    "you"
  ],
  "small": {
    "scale": 2.8299999999999934,
    "offset_x": -839.0666666666666,
    "offset_y": -273.1999999999999,
    "size": "small",
    "rotation": 0
  },
  "medium": {
    "scale": 1.9700000000000009,
    "offset_x": -493,
    "offset_y": -170.19999999999993,
    "size": "medium",
    "rotation": 0
  },
  "full": {
    "scale": 2.6899999999999875,
    "offset_x": -594.287037037037,
    "offset_y": -36.84259259259261,
    "size": "full",
    "rotation": 0
  },
  "version": 2,
  "requeried": false,
  "nsfw": false
}