{
  "source": "https://cdn.donmai.us/original/1e/b2/__mei_mei_jujutsu_kaisen_drawn_by_zaki_zaki_btw__1eb2135b9253d46015c6152c81452fee.jpg",
  "md5": "1EB2135B9253D46015C6152C81452FEE",
  "tags": [
    ""
  ],
  "small": {
    "scale": 0.27999999999999964,
    "offset_x": -295,
    "offset_y": -60,
    "size": "small"
  },
  "medium": {
    "scale": 0.16999999999999946,
    "offset_x": -47,
    "offset_y": 0,
    "size": "medium"
  },
  "full": {
    "scale": 0.27999999999999936,
    "offset_x": -6,
    "offset_y": 0,
    "size": "full"
  },
  "version": 2,
  "requeried": false,
  "nsfw": false
}