{
  "source": "https://i.pinimg.com/736x/b4/71/0c/b4710c382a452349fecb639de07f9100.jpg",
  "md5": "973DD968434400A67C70BEE94B673D86",
  "tags": [
    ""
  ],
  "small": {
    "scale": 1.8200000000000007,
    "offset_x": -348,
    "offset_y": -153,
    "size": "small",
    "rotation": 0
  },
  "medium": {
    "scale": 0.8299999999999998,
    "offset_x": -101,
    "offset_y": -41,
    "size": "medium",
    "rotation": 0
  },
  "full": {
    "scale": 1.3400000000000003,
    "offset_x": -42,
    "offset_y": -4,
    "size": "full",
    "rotation": 0
  },
  "version": 2,
  "requeried": false,
  "nsfw": false
}