{
  "source": "https://cdnb.artstation.com/p/assets/images/images/004/338/877/large/wisnu-tan-demon-gentleman-reg-uplox.jpg?1482634173",
  "md5": "349A2042F50AFEA73AAD8D1E8A84C6A8",
  "tags": [
    "",
    "devil",
    "frog",
    "toavffhf"
  ],
  "small": {
    "scale": 0.49999999999999956,
    "offset_x": -272,
    "offset_y": -121,
    "size": "small",
    "rotation": 0
  },
  "medium": {
    "scale": 0.3099999999999994,
    "offset_x": -77,
    "offset_y": -14,
    "size": "medium",
    "rotation": 0
  },
  "full": {
    "scale": 0.5699999999999996,
    "offset_x": -94,
    "offset_y": -10,
    "size": "full",
    "rotation": 0
  },
  "version": 2,
  "requeried": false,
  "nsfw": false
}