{
  "source": "https://i.imgur.com/sEi0QFo.png",
  "md5": "BBA198A5CBF89BDFB24A3EE3DE3BDBC5",
  "tags": [
    ""
  ],
  "small": {
    "scale": 0.46999999999999953,
    "offset_x": -115,
    "offset_y": -13,
    "size": "small",
    "rotation": 0
  },
  "medium": {
    "scale": 0.4599999999999995,
    "offset_x": -39,
    "offset_y": -18,
    "size": "medium",
    "rotation": 0
  },
  "full": {
    "scale": 0.8299999999999998,
    "offset_x": -20,
    "offset_y": -12,
    "size": "full",
    "rotation": 0
  },
  "version": 2,
  "requeried": false,
  "nsfw": false
}