{
  "source": "https://tocusfj.opzvkgjekiwr.hath.network/h/71eec3f112bd8c9b4930a118046614485b92467f-248577-1280-1920-jpg/keystamp=1648878000-ded476fd49;fileindex=88392951;xres=1280/2b3.jpg",
  "md5": "CB731DE1D8E6FD647B94EACDFC9B0E04",
  "tags": [
    ""
  ],
  "small": {
    "scale": 0.3399999999999994,
    "offset_x": -125,
    "offset_y": -4,
    "size": "small",
    "rotation": 0
  },
  "medium": {
    "scale": 0.3099999999999994,
    "offset_x": -33,
    "offset_y": -3,
    "size": "medium",
    "rotation": 0
  },
  "full": {
    "scale": 0.5499999999999996,
    "offset_x": -8,
    "offset_y": -6,
    "size": "full",
    "rotation": 0
  },
  "version": 2,
  "requeried": false,
  "nsfw": false
}