{
  "source": "https://i.imgur.com/0wYAJnK.png",
  "md5": "3B89E9E533981E6E0FA612B329786399",
  "tags": [
    ""
  ],
  "small": {
    "scale": 0.36999999999999944,
    "offset_x": -202,
    "offset_y": -38,
    "size": "small",
    "rotation": 0
  },
  "medium": {
    "scale": 0.4599999999999995,
    "offset_x": -190,
    "offset_y": -21,
    "size": "medium",
    "rotation": 0
  },
  "full": {
    "scale": 0.9199999999999999,
    "offset_x": -404,
    "offset_y": -10,
    "size": "full",
    "rotation": 0
  },
  "version": 2,
  "requeried": false,
  "nsfw": false
}