{
  "source": "https://i.pinimg.com/564x/12/f8/8e/12f88e5841c6382c515f61fc37649ce5.jpg",
  "md5": "6325BD016F30990432841330AAC1346E",
  "tags": [
    ""
  ],
  "small": {
    "scale": 0.3499999999999994,
    "offset_x": -7,
    "offset_y": -14,
    "size": "small",
    "rotation": 0
  },
  "medium": {
    "scale": 0.5999999999999996,
    "offset_x": 0,
    "offset_y": -8,
    "size": "medium",
    "rotation": 0
  },
  "full": {
    "scale": 1.3600000000000003,
    "offset_x": -46,
    "offset_y": -30,
    "size": "full",
    "rotation": 0
  },
  "version": 2,
  "requeried": false,
  "nsfw": false
}