{
  "source": "https://cdna.artstation.com/p/assets/images/images/006/523/170/large/bangku-an-dam-01.jpg?1499247264",
  "md5": "AE7799DECC0A60C98BE8C0678E1F6DD0",
  "tags": [
    "",
    "anime",
    "girl",
    "concept",
    "character",
    "warrior",
    "high",
    "elf",
    "female",
    "pirate",
    "practice",
    "liu",
    "gang",
    "https://www.artstation",
    "anisha",
    "kang",
    "jihun",
    "tatiana",
    "vetrova\u0027s",
    "submission",
    "ancient"
  ],
  "small": {
    "scale": 0.9199999999999999,
    "offset_x": -869.5999999999926,
    "offset_y": -328.80000000000007,
    "size": "small",
    "rotation": 0
  },
  "medium": {
    "scale": 0.38999999999999946,
    "offset_x": -256.00000000000006,
    "offset_y": -120,
    "size": "medium",
    "rotation": 0
  },
  "full": {
    "scale": 0.37999999999999945,
    "offset_x": -35.24074074074042,
    "offset_y": -81.69444444444446,
    "size": "full",
    "rotation": 0
  },
  "version": 2,
  "requeried": true,
  "nsfw": false
}