{
  "source": "https://www.cuded.com/wp-content/uploads/2013/04/Cardinal.jpg",
  "md5": "5CD3B98266A1F6566C1A2273B2FAB4EF",
  "tags": [
    "ravenloft",
    "artwork",
    "elf",
    "character",
    "portraits",
    "human_made_object",
    "fashion_cosmetics_or_accessories",
    "accessories",
    "jewelry",
    "necklace"
  ],
  "small": {
    "scale": 1.01,
    "offset_x": -245,
    "offset_y": -147,
    "size": "small",
    "rotation": 0
  },
  "medium": {
    "scale": 0.8099999999999998,
    "offset_x": -124,
    "offset_y": -102,
    "size": "medium",
    "rotation": 0
  },
  "full": {
    "scale": 1.1700000000000002,
    "offset_x": -2,
    "offset_y": -4,
    "size": "full",
    "rotation": 0
  },
  "version": 2,
  "requeried": false,
  "nsfw": false
}