{
  "source": "https://artfiles.alphacoders.com/377/thumb-1920-37778.jpg",
  "md5": "6AC6EEEFA54B8F8D1CA0BE142162686E",
  "tags": [
    "aennye",
    "hobbyist",
    "digital",
    "artist",
    "consumerstarfish",
    "user",
    "profile",
    "sexy",
    "girl",
    "3d"
  ],
  "small": {
    "scale": 0.5899999999999996,
    "offset_x": -183,
    "offset_y": -84,
    "size": "small"
  },
  "medium": {
    "scale": 0.6599999999999997,
    "offset_x": -137,
    "offset_y": -94,
    "size": "medium"
  },
  "full": {
    "scale": 1.2699999999999998,
    "offset_x": -155,
    "offset_y": -177,
    "size": "full"
  },
  "version": 2,
  "requeried": false,
  "nsfw": false
}