{
  "source": "https://cdnb.artstation.com/p/assets/images/images/059/540/555/large/alexandr-voytsekhovskiy-photo-2023-02-17-03-10-06.jpg?1676595607",
  "md5": "81CBE01FEDD05CE6F83AE61A7E18322C",
  "tags": [
    ""
  ],
  "small": {
    "scale": 0.5099999999999996,
    "offset_x": -357,
    "offset_y": -208,
    "size": "small",
    "rotation": 0
  },
  "medium": {
    "scale": 0.28999999999999937,
    "offset_x": -56,
    "offset_y": -75,
    "size": "medium",
    "rotation": 0
  },
  "full": {
    "scale": 0.48999999999999955,
    "offset_x": -44,
    "offset_y": -140,
    "size": "full",
    "rotation": 0
  },
  "version": 2,
  "requeried": false,
  "nsfw": false
}