{
  "source": "https://i.pinimg.com/564x/f2/ba/35/f2ba350f78ed599172d4d4911ad387e5.jpg",
  "md5": "DF31E84E384EC5A621AE9F967D37BE6C",
  "tags": [
    "cryptic",
    "command",
    "mtg",
    "tower",
    "zurgo",
    "time",
    "mage",
    "fan",
    "jing",
    "anime",
    "artwork",
    "overwatch",
    "wallpapers",
    "angel",
    "mercy",
    "oc",
    "azareiah",
    "lera",
    "pi",
    "with"
  ],
  "small": {
    "scale": 1.3800000000000003,
    "offset_x": -308,
    "offset_y": -167,
    "size": "small",
    "rotation": 0
  },
  "medium": {
    "scale": 0.6499999999999997,
    "offset_x": -35,
    "offset_y": -42,
    "size": "medium",
    "rotation": 0
  },
  "full": {
    "scale": 1.3500000000000003,
    "offset_x": -69,
    "offset_y": -104,
    "size": "full",
    "rotation": 0
  },
  "version": 2,
  "requeried": false,
  "nsfw": false
}