{
  "source": "https://pbs.twimg.com/media/EOPVgQEUcAA2XTa.jpg",
  "md5": "1AB70C93F181FA5C3DAB6070E35F4C5B",
  "tags": [
    "person",
    "human",
    "helmet",
    "clothing",
    "apparel",
    "samurai",
    "knight",
    "ninja",
    ""
  ],
  "small": {
    "scale": 0.6999999999999997,
    "offset_x": -245,
    "offset_y": -4,
    "size": "small"
  },
  "medium": {
    "scale": 0.6599999999999997,
    "offset_x": -163,
    "offset_y": -2,
    "size": "medium"
  },
  "full": {
    "scale": 1.02,
    "offset_x": -157,
    "offset_y": -3,
    "size": "full"
  },
  "version": 2
}