{
  "source": "https://pbs.twimg.com/media/EaOGryYUYAEZhas?format=jpg&name=4096x4096",
  "md5": "8A8243E0E2348BFE8DF045A89B8949F8",
  "tags": [
    "archer",
    "archery",
    "person",
    "bow",
    "sport",
    "human",
    "sports",
    "toy",
    "Scythe"
  ],
  "small": {
    "scale": 0.3599999999999995,
    "offset_x": -592,
    "offset_y": -263,
    "size": "small"
  },
  "medium": {
    "scale": 0.2899999999999996,
    "offset_x": -366,
    "offset_y": -165,
    "size": "medium"
  },
  "full": {
    "scale": 0.29999999999999954,
    "offset_x": -242,
    "offset_y": -104,
    "size": "full"
  },
  "version": 2
}