{
  "source": "https://cdnb.artstation.com/p/assets/images/images/005/550/361/large/grace-park-knight.jpg?1491894401",
  "md5": "A60714B2793408E2D79283CBAA1A6EDD",
  "tags": [
    "dark",
    "knight",
    "concept",
    "fan",
    "artwork",
    "captain",
    "america",
    "winter",
    "soldier",
    "armor",
    "guardians",
    "ga",
    "hoole",
    "game",
    "thrones",
    "medieval",
    "knights",
    "human_made_object",
    "fashion_cosmetics_or_accessories",
    "clothing",
    "outer_wear",
    "jacket",
    "alistair",
    "anton",
    "fort",
    "2020",
    "batman",
    "dawn",
    "justice",
    "bruno",
    "furlani"
  ],
  "small": {
    "scale": 0.5199999999999996,
    "offset_x": -438,
    "offset_y": -80,
    "size": "small"
  },
  "medium": {
    "scale": 0.38999999999999946,
    "offset_x": -233,
    "offset_y": -69,
    "size": "medium"
  },
  "full": {
    "scale": 0.5699999999999996,
    "offset_x": -240,
    "offset_y": -82,
    "size": "full"
  },
  "version": 2,
  "requeried": false,
  "nsfw": false
}