{
  "source": "https://i.pinimg.com/564x/91/b0/45/91b04527bf1fd2ec2d6943ba34d084fe.jpg",
  "md5": "1A189BD5D820F6FA3B4E722D7D20F30D",
  "tags": [
    ""
  ],
  "small": {
    "scale": 0.6499999999999997,
    "offset_x": -47,
    "offset_y": -2,
    "size": "small",
    "rotation": 0
  },
  "medium": {
    "scale": 1,
    "offset_x": -96,
    "offset_y": -4,
    "size": "medium",
    "rotation": 0
  },
  "full": {
    "scale": 1.3800000000000003,
    "offset_x": -56,
    "offset_y": -30,
    "size": "full",
    "rotation": 0
  },
  "version": 2,
  "requeried": false,
  "nsfw": false
}